autheon/__init__.py
autheon/adapters/__init__.py
autheon/adapters/fastapi/__init__.py
autheon/adapters/fastapi/csrf_middleware.py
autheon/adapters/fastapi/flow.py
autheon/adapters/fastapi/route.py
autheon/adapters/fastapi/use_response.py
autheon/adapters/use_response.py
autheon/authorize.py
autheon/callback.py
autheon/config.py
autheon/const_data.py
autheon/cookies.py
autheon/csrf.py
autheon/exceptions.py
autheon/jwts/__init__.py
autheon/jwts/handler.py
autheon/jwts/helpers.py
autheon/jwts/operations.py
autheon/libtypes.py
autheon/log.py
autheon/oauth2_baseflow.py
autheon/oauth2_options.py
autheon/providers/__init__.py
autheon/providers/base.py
autheon/providers/google/__init__.py
autheon/providers/google/google.py
autheon/providers/google/schemas.py
autheon/providers/spotify/__init__.py
autheon/providers/spotify/schemas.py
autheon/py.typed
autheon/signin.py
autheon/signout.py
autheon/utils.py
autheon-0.0.0.dist-info/LICENSE
autheon-0.0.0.dist-info/METADATA
autheon-0.0.0.dist-info/WHEEL
autheon-0.0.0.dist-info/RECORD
