Metadata-Version: 2.3
Name: autheon
Version: 0.0.0
Summary: OAuth2 3rd party integration libray for your favorite framework
License: MIT
Author: Ashref Gwader
Author-email: oss@ashgw.me
Requires-Python: >=3.10,<4.0
Classifier: Development Status :: 4 - Beta
Classifier: Intended Audience :: Developers
Classifier: License :: OSI Approved :: MIT License
Classifier: Programming Language :: Python :: 3 :: Only
Classifier: Programming Language :: Python :: 3.10
Classifier: Programming Language :: Python :: 3.11
Classifier: Programming Language :: Python :: 3.12
Classifier: Programming Language :: Python :: 3.13
Classifier: Typing :: Typed
Requires-Dist: email-validator (>=2.1.0.post1,<3.0.0)
Requires-Dist: fastapi (>=0.93.0,<0.94.0)
Requires-Dist: httpx (>=0.23.2,<0.24.0)
Requires-Dist: overrides (>=7.6.0,<8.0.0)
Requires-Dist: python-jose[cryptography] (>=3.1.0,<4.0.0)
Project-URL: Changelog, https://github.com/ashgw/fastauth/releases
Project-URL: Documentation, https://ashgw.github.io/fastauth/
Project-URL: Homepage, https://ashgw.github.io/fastauth/
Project-URL: Source, https://github.com/ashgw/fastauth
